rep_cli/database.py
rep_cli/main.py
rep_cli/models.py
rep_cli-0.1.2.dist-info/entry_points.txt
rep_cli-0.1.2.dist-info/LICENSE.txt
rep_cli-0.1.2.dist-info/WHEEL
rep_cli-0.1.2.dist-info/METADATA
rep_cli-0.1.2.dist-info/RECORD
