Metadata-Version: 2.1
Name: rep-cli
Version: 0.1.2
Summary: A tiny tool for freelancers and contractors for tracking time and calculating invoices.
License: MIT
Author: Wojciech Bogócki
Author-email: wojciechbogocki@fastmail.com
Requires-Python: >=3.8,<4.0
Classifier: License :: OSI Approved :: MIT License
Classifier: Programming Language :: Python :: 3
Classifier: Programming Language :: Python :: 3.8
Classifier: Programming Language :: Python :: 3.9
Requires-Dist: pydantic (>=1.7.1,<2.0.0)
Requires-Dist: shellingham (>=1.3.2,<2.0.0)
Requires-Dist: tabulate (>=0.8.7,<0.9.0)
Requires-Dist: tinydb (>=4.2.0,<5.0.0)
Requires-Dist: tinydb-serialization (>=2.0.0,<3.0.0)
Requires-Dist: typer (>=0.3.2,<0.4.0)
Requires-Dist: wcwidth (>=0.2.5,<0.3.0)
